test_pypi_tonywu71/__init__.py
test_pypi_tonywu71/example.py
test_pypi_tonywu71-0.1.0.dist-info/METADATA
test_pypi_tonywu71-0.1.0.dist-info/WHEEL
test_pypi_tonywu71-0.1.0.dist-info/RECORD
