Metadata-Version: 2.3
Name: test-pypi-tonywu71
Version: 0.1.0
Summary: Test
Author: Tony Wu
Classifier: Intended Audience :: Developers
Classifier: Intended Audience :: Science/Research
Classifier: License :: OSI Approved :: MIT License
Classifier: Programming Language :: Python :: 3
Classifier: Topic :: Scientific/Engineering :: Artificial Intelligence
Classifier: Typing :: Typed
Requires-Python: >=3.11.6
Requires-Dist: typer>=0.12.3
